txppb/__init__.py
txppb-0.1.dist-info/LICENSE.txt
txppb-0.1.dist-info/METADATA
txppb-0.1.dist-info/WHEEL
txppb-0.1.dist-info/top_level.txt
txppb-0.1.dist-info/RECORD
