Metadata-Version: 2.1
Name: txppb
Version: 0.1
Summary: Twisted support for PursuedPyBear
Home-page: https://github.com/moshez/txppb
Author: Moshe Zadka
Author-email: moshez@zadka.club
License: Artistic-2.0
Platform: UNKNOWN
Classifier: Development Status :: 4 - Beta
Classifier: Intended Audience :: Education
Classifier: Intended Audience :: Developers
Classifier: License :: OSI Approved :: Artistic License
Classifier: Natural Language :: English
Classifier: Programming Language :: Python :: 3
Classifier: Programming Language :: Python :: 3.6
Classifier: Programming Language :: Python :: 3.7
Classifier: Programming Language :: Python :: 3.8
Classifier: Topic :: Games/Entertainment
Classifier: Topic :: Software Development :: Libraries
Classifier: Operating System :: OS Independent
Requires-Python: >= 3.6
Requires-Dist: Twisted
Requires-Dist: ppb
